too_simple_server/__init__.py
too_simple_server/__main__.py
too_simple_server/api.py
too_simple_server/configuration.py
too_simple_server/database.py
too_simple_server/run.py
too_simple_server-0.2.5.dist-info/LICENSE
too_simple_server-0.2.5.dist-info/WHEEL
too_simple_server-0.2.5.dist-info/METADATA
too_simple_server-0.2.5.dist-info/RECORD
