Metadata-Version: 2.1
Name: too-simple-server
Version: 0.2.5
Summary: Simple web server stub for testing purposes (with a lot of dependencies)
License: Apache-2.0
Author: Anton Kachurin
Author-email: anton.kachurin@t-systems.com
Requires-Python: >=3.6.1,<4.0.0
Classifier: License :: OSI Approved :: Apache Software License
Classifier: Programming Language :: Python :: 3
Classifier: Programming Language :: Python :: 3.7
Requires-Dist: dataclasses (>=0.6.0,<0.7.0); python_version >= "3.6" and python_version < "3.7"
Requires-Dist: docutils (==0.14)
Requires-Dist: flask (>=1.1,<2.0)
Requires-Dist: lockfile (>=0.12.2,<0.13.0)
Requires-Dist: ocomone (>=0.3.1,<0.4.0)
Requires-Dist: peewee (>=3.9,<4.0)
Requires-Dist: psycopg2-binary (>=2.8,<3.0)
Requires-Dist: python-daemon (>=2.2,<3.0)
Requires-Dist: pyyaml (>=5.1,<6.0)
Requires-Dist: requests (>=2.22,<3.0)
Requires-Dist: wsgiserver (>=1.3,<2.0)
